emeralx/__init__.py
emeralx/audio.py
emeralx/canvas.py
emeralx/display.py
emeralx/entity.py
emeralx/events.py
emeralx/image.py
emeralx/resources/default.ttf
emeralx/resources/logo.png
emeralx-0.9.2.dist-info/licenses/LICENSE
emeralx-0.9.2.dist-info/METADATA
emeralx-0.9.2.dist-info/WHEEL
emeralx-0.9.2.dist-info/top_level.txt
emeralx-0.9.2.dist-info/RECORD
