Metadata-Version: 2.4
Name: emeralx
Version: 0.9.2
Summary: A library for making simple 2D games, an advanced version for Emeral
Author: modaochangyang
Author-email: 1602422136@qq.com
License: MIT
Keywords: emeralx
Classifier: License :: OSI Approved :: MIT License
Classifier: Programming Language :: Python :: 3
Classifier: Programming Language :: Python :: 3.7
Classifier: Programming Language :: Python :: 3.8
Classifier: Programming Language :: Python :: 3.9
Classifier: Programming Language :: Python :: 3.10
Requires-Python: >=3.7
License-File: LICENSE
Requires-Dist: pygame>=2.5.0
Requires-Dist: pywin32>=306
Requires-Dist: numpy>=1.24.0
Requires-Dist: Pillow>=10.0.0
Dynamic: author
Dynamic: author-email
Dynamic: classifier
Dynamic: description
Dynamic: description-content-type
Dynamic: keywords
Dynamic: license
Dynamic: license-file
Dynamic: requires-dist
Dynamic: requires-python
Dynamic: summary
